rememepy/__init__.py
rememepy/substitution.py
rememepy/supporting_functions.py
rememepy-0.1.4.dist-info/licenses/LICENSE
rememepy-0.1.4.dist-info/METADATA
rememepy-0.1.4.dist-info/WHEEL
rememepy-0.1.4.dist-info/top_level.txt
rememepy-0.1.4.dist-info/RECORD
