Metadata-Version: 2.4
Name: rememepy
Version: 0.1.4
Summary: A tool to substitute the main image in memes.
Author-email: Robin Škába <robin.skaba@gmail.com>
License-Expression: MIT
Project-URL: Homepage, https://github.com/robinskaba/rememepy
Requires-Python: >=3.10
License-File: LICENSE
Requires-Dist: numpy>=1.26.0
Requires-Dist: pillow>=11.2.1
Requires-Dist: scipy>=1.15.0
Dynamic: license-file
